nwpy/__init__.py
nwpy/nwpy.py
nwpy-0.8.dist-info/METADATA
nwpy-0.8.dist-info/WHEEL
nwpy-0.8.dist-info/entry_points.txt
nwpy-0.8.dist-info/top_level.txt
nwpy-0.8.dist-info/RECORD
